{"generated":"2026-05-30T22:06:40.419186+00:00","total":75,"players":[{"rank":1,"name":"Viallinen","points":96040,"regions":["Varlamore","Karamja","Kandarin","Tirannwn","Kebos and Kourend"]},{"rank":2,"name":"B0aty","points":96040,"regions":["Varlamore","Karamja","Kandarin","Tirannwn","Kebos and Kourend"]},{"rank":3,"name":"crueship","points":96040,"regions":["Varlamore","Karamja","Kandarin","Tirannwn","Kebos and Kourend"]},{"rank":4,"name":"Ge8ff","points":96040,"regions":["Varlamore","Karamja","Kandarin","Tirannwn","Kebos and Kourend"]},{"rank":5,"name":"Knuupy","points":96040,"regions":["Varlamore","Karamja","Kandarin","Desert","Kebos and Kourend"]},{"rank":6,"name":"GHERKINS","points":96040,"regions":["Varlamore","Karamja","Kandarin","Tirannwn","Kebos and Kourend"]},{"rank":7,"name":"DontPanicPlx","points":96040,"regions":["Varlamore","Karamja","Kandarin","Tirannwn","Kebos and Kourend"]},{"rank":8,"name":"yezplz","points":96040,"regions":["Varlamore","Karamja","Kandarin","Tirannwn","Kebos and Kourend"]},{"rank":9,"name":"A Cold One","points":96040,"regions":["Varlamore","Karamja","Kandarin","Tirannwn","Kebos and Kourend"]},{"rank":10,"name":"Jcw","points":96040,"regions":["Varlamore","Karamja","Kandarin","Tirannwn","Kebos and Kourend"]},{"rank":11,"name":"Two2SixToo","points":96040,"regions":["Varlamore","Karamja","Kandarin","Tirannwn","Kebos and Kourend"]},{"rank":12,"name":"Slinkey","points":96040,"regions":["Varlamore","Karamja","Kandarin","Tirannwn","Kebos and Kourend"]},{"rank":13,"name":"Noobalhao","points":96040,"regions":["Varlamore","Karamja","Kandarin","Tirannwn","Kebos and Kourend"]},{"rank":14,"name":"Ironic_Memes","points":96040,"regions":["Varlamore","Karamja","Kandarin","Desert","Kebos and Kourend"]},{"rank":15,"name":"papaya farm","points":96040,"regions":["Varlamore","Karamja","Kandarin","Tirannwn","Kebos and Kourend"]},{"rank":16,"name":"Insanewolfy","points":96040,"regions":["Varlamore","Karamja","Kandarin","Desert","Kebos and Kourend"]},{"rank":17,"name":"Squat Slav","points":96040,"regions":["Varlamore","Karamja","Kandarin","Tirannwn","Kebos and Kourend"]},{"rank":18,"name":"RobDownsyJr","points":96040,"regions":["Varlamore","Karamja","Kandarin","Tirannwn","Kebos and Kourend"]},{"rank":19,"name":"SheHerbiboar","points":96040,"regions":["Varlamore","Karamja","Kandarin","Tirannwn","Kebos and Kourend"]},{"rank":20,"name":"Pocket Dough","points":96040,"regions":["Varlamore","Karamja","Kandarin","Tirannwn","Kebos and Kourend"]},{"rank":21,"name":"gregs nut","points":96040,"regions":["Varlamore","Karamja","Kandarin","Tirannwn","Kebos and Kourend"]},{"rank":22,"name":"Teaa Cup","points":96040,"regions":["Varlamore","Karamja","Kandarin","Tirannwn","Kebos and Kourend"]},{"rank":23,"name":"Wise Old Pal","points":96040,"regions":["Varlamore","Karamja","Kandarin","Tirannwn","Kebos and Kourend"]},{"rank":24,"name":"Baaze","points":96040,"regions":["Varlamore","Karamja","Kandarin","Tirannwn","Kebos and Kourend"]},{"rank":25,"name":"catsleep","points":96040,"regions":["Varlamore","Karamja","Kandarin","Tirannwn","Kebos and Kourend"]},{"rank":26,"name":"Gl Im Tom","points":96040,"regions":["Varlamore","Karamja","Kandarin","Tirannwn","Kebos and Kourend"]},{"rank":27,"name":"Pole Met","points":96040,"regions":["Varlamore","Karamja","Kandarin","Tirannwn","Kebos and Kourend"]},{"rank":28,"name":"Fehz","points":96040,"regions":["Varlamore","Karamja","Kandarin","Desert","Kebos and Kourend"]},{"rank":29,"name":"Schokotraum","points":96040,"regions":["Varlamore","Karamja","Kandarin","Tirannwn","Kebos and Kourend"]},{"rank":30,"name":"KiwiIskadda","points":96040,"regions":["Varlamore","Karamja","Kandarin","Tirannwn","Kebos and Kourend"]},{"rank":31,"name":"Anditre","points":96040,"regions":["Varlamore","Karamja","Kandarin","Tirannwn","Kebos and Kourend"]},{"rank":32,"name":"Usva","points":96040,"regions":["Varlamore","Karamja","Kandarin","Tirannwn","Kebos and Kourend"]},{"rank":33,"name":"Seanz","points":96040,"regions":["Varlamore","Karamja","Kandarin","Tirannwn","Kebos and Kourend"]},{"rank":34,"name":"Humble Otter","points":96040,"regions":["Varlamore","Karamja","Kandarin","Tirannwn","Kebos and Kourend"]},{"rank":35,"name":"DMMonkfish","points":96040,"regions":["Varlamore","Karamja","Kandarin","Tirannwn","Kebos and Kourend"]},{"rank":36,"name":"Figuur","points":96040,"regions":["Varlamore","Karamja","Kandarin","Tirannwn","Kebos and Kourend"]},{"rank":37,"name":"ImAGwiyomi","points":96040,"regions":["Varlamore","Karamja","Kandarin","Tirannwn","Kebos and Kourend"]},{"rank":38,"name":"Scottie","points":96040,"regions":["Varlamore","Karamja","Kandarin","Tirannwn","Kebos and Kourend"]},{"rank":39,"name":"Tokkul Hole","points":96040,"regions":["Varlamore","Karamja","Kandarin","Tirannwn","Kebos and Kourend"]},{"rank":40,"name":"Tyst","points":96040,"regions":["Varlamore","Karamja","Fremennik Province","Kandarin","Kebos and Kourend"]},{"rank":41,"name":"Ranger Lemus","points":96040,"regions":["Varlamore","Karamja","Kandarin","Tirannwn","Kebos and Kourend"]},{"rank":42,"name":"Molten B","points":96040,"regions":["Varlamore","Karamja","Kandarin","Tirannwn","Kebos and Kourend"]},{"rank":43,"name":"Exarch","points":96040,"regions":["Varlamore","Karamja","Kandarin","Tirannwn","Kebos and Kourend"]},{"rank":44,"name":"Satamario","points":96040,"regions":["Varlamore","Karamja","Kandarin","Tirannwn","Kebos and Kourend"]},{"rank":45,"name":"Maverick Btw","points":96040,"regions":["Varlamore","Karamja","Kandarin","Tirannwn","Kebos and Kourend"]},{"rank":46,"name":"Trattil","points":96040,"regions":["Varlamore","Karamja","Asgarnia","Kandarin","Morytania"]},{"rank":47,"name":"Opayye","points":96040,"regions":["Varlamore","Karamja","Asgarnia","Kandarin","Kebos and Kourend"]},{"rank":48,"name":"Psychia Tree","points":96040,"regions":["Varlamore","Karamja","Kandarin","Desert","Kebos and Kourend"]},{"rank":49,"name":"dippy eggs","points":96040,"regions":["Varlamore","Karamja","Kandarin","Tirannwn","Kebos and Kourend"]},{"rank":50,"name":"Kilzu","points":96040,"regions":["Varlamore","Karamja","Kandarin","Tirannwn","Kebos and Kourend"]},{"rank":51,"name":"Zekkels","points":96040,"regions":["Varlamore","Karamja","Kandarin","Tirannwn","Kebos and Kourend"]},{"rank":52,"name":"AG up ur S","points":96040,"regions":["Varlamore","Karamja","Kandarin","Tirannwn","Kebos and Kourend"]},{"rank":53,"name":"Slick Lenny","points":96040,"regions":["Varlamore","Karamja","Kandarin","Tirannwn","Kebos and Kourend"]},{"rank":54,"name":"Wardy791","points":96040,"regions":["Varlamore","Karamja","Kandarin","Tirannwn","Kebos and Kourend"]},{"rank":55,"name":"BEATONiT","points":96040,"regions":["Varlamore","Karamja","Kandarin","Desert","Kebos and Kourend"]},{"rank":56,"name":"MugiWugi","points":96040,"regions":["Varlamore","Karamja","Kandarin","Tirannwn","Kebos and Kourend"]},{"rank":57,"name":"Anglerfish43","points":96040,"regions":["Varlamore","Karamja","Kandarin","Tirannwn","Kebos and Kourend"]},{"rank":58,"name":"Goodfellow","points":96040,"regions":["Varlamore","Karamja","Kandarin","Tirannwn","Kebos and Kourend"]},{"rank":59,"name":"Tickflow","points":96040,"regions":["Varlamore","Karamja","Kandarin","Tirannwn","Kebos and Kourend"]},{"rank":60,"name":"chud monkey","points":96040,"regions":["Varlamore","Karamja","Kandarin","Tirannwn","Kebos and Kourend"]},{"rank":61,"name":"Iron Laura1","points":96040,"regions":["Varlamore","Karamja","Kandarin","Tirannwn","Kebos and Kourend"]},{"rank":62,"name":"Suplybox","points":96040,"regions":["Varlamore","Karamja","Kandarin","Tirannwn","Kebos and Kourend"]},{"rank":63,"name":"I was Krazy","points":96040,"regions":["Varlamore","Karamja","Kandarin","Tirannwn","Kebos and Kourend"]},{"rank":64,"name":"WIDE POGGIES","points":96040,"regions":["Varlamore","Karamja","Kandarin","Tirannwn","Kebos and Kourend"]},{"rank":65,"name":"Glooknar","points":96040,"regions":["Varlamore","Karamja","Kandarin","Tirannwn","Kebos and Kourend"]},{"rank":66,"name":"ruorimies","points":96040,"regions":["Varlamore","Karamja","Kandarin","Tirannwn","Kebos and Kourend"]},{"rank":67,"name":"Twirlylimon","points":96040,"regions":["Varlamore","Karamja","Kandarin","Tirannwn","Kebos and Kourend"]},{"rank":68,"name":"Crangus","points":96040,"regions":["Varlamore","Karamja","Kandarin","Morytania","Tirannwn"]},{"rank":69,"name":"Corgi Puppy","points":96040,"regions":["Varlamore","Karamja","Kandarin","Tirannwn","Kebos and Kourend"]},{"rank":70,"name":"Dohdee","points":96040,"regions":["Varlamore","Karamja","Kandarin","Tirannwn","Kebos and Kourend"]},{"rank":71,"name":"Losel","points":96040,"regions":["Varlamore","Karamja","Kandarin","Tirannwn","Kebos and Kourend"]},{"rank":72,"name":"LGBTQIDGAF","points":96040,"regions":["Varlamore","Karamja","Kandarin","Tirannwn","Kebos and Kourend"]},{"rank":73,"name":"Iron_Nino07","points":96040,"regions":["Varlamore","Karamja","Kandarin","Tirannwn","Kebos and Kourend"]},{"rank":74,"name":"Mina Heart 2","points":96040,"regions":["Varlamore","Karamja","Kandarin","Tirannwn","Kebos and Kourend"]},{"rank":75,"name":"Jettrider","points":96040,"regions":["Varlamore","Karamja","Kandarin","Tirannwn","Kebos and Kourend"]}]}