{"generated":"2026-05-13T09:32:09.703718+00:00","total":500,"players":[{"rank":1,"name":"Viallinen","points":96040,"regions":["Varlamore","Karamja","Kandarin","Tirannwn","Kebos and Kourend"]},{"rank":2,"name":"B0aty","points":96040,"regions":["Varlamore","Karamja","Kandarin","Tirannwn","Kebos and Kourend"]},{"rank":3,"name":"crueship","points":96040,"regions":["Varlamore","Karamja","Kandarin","Tirannwn","Kebos and Kourend"]},{"rank":4,"name":"Ge8ff","points":96040,"regions":["Varlamore","Karamja","Kandarin","Tirannwn","Kebos and Kourend"]},{"rank":5,"name":"Knuupy","points":96040,"regions":["Varlamore","Karamja","Kandarin","Desert","Kebos and Kourend"]},{"rank":6,"name":"GHERKINS","points":96040,"regions":["Varlamore","Karamja","Kandarin","Tirannwn","Kebos and Kourend"]},{"rank":7,"name":"DontPanicPlx","points":96040,"regions":["Varlamore","Karamja","Kandarin","Tirannwn","Kebos and Kourend"]},{"rank":8,"name":"yezplz","points":96040,"regions":["Varlamore","Karamja","Kandarin","Tirannwn","Kebos and Kourend"]},{"rank":9,"name":"A Cold One","points":96040,"regions":["Varlamore","Karamja","Kandarin","Tirannwn","Kebos and Kourend"]},{"rank":10,"name":"Jcw","points":96040,"regions":["Varlamore","Karamja","Kandarin","Tirannwn","Kebos and Kourend"]},{"rank":11,"name":"Two2SixToo","points":96040,"regions":["Varlamore","Karamja","Kandarin","Tirannwn","Kebos and Kourend"]},{"rank":12,"name":"Slinkey","points":96040,"regions":["Varlamore","Karamja","Kandarin","Tirannwn","Kebos and Kourend"]},{"rank":13,"name":"Noobalhao","points":96040,"regions":["Varlamore","Karamja","Kandarin","Tirannwn","Kebos and Kourend"]},{"rank":14,"name":"Ironic_Memes","points":96040,"regions":["Varlamore","Karamja","Kandarin","Desert","Kebos and Kourend"]},{"rank":15,"name":"papaya farm","points":96040,"regions":["Varlamore","Karamja","Kandarin","Tirannwn","Kebos and Kourend"]},{"rank":16,"name":"Insanewolfy","points":96040,"regions":["Varlamore","Karamja","Kandarin","Desert","Kebos and Kourend"]},{"rank":17,"name":"Squat Slav","points":96040,"regions":["Varlamore","Karamja","Kandarin","Tirannwn","Kebos and Kourend"]},{"rank":18,"name":"RobDownsyJr","points":96040,"regions":["Varlamore","Karamja","Kandarin","Tirannwn","Kebos and Kourend"]},{"rank":19,"name":"SheHerbiboar","points":96040,"regions":["Varlamore","Karamja","Kandarin","Tirannwn","Kebos and Kourend"]},{"rank":20,"name":"Pocket Dough","points":96040,"regions":["Varlamore","Karamja","Kandarin","Tirannwn","Kebos and Kourend"]},{"rank":21,"name":"gregs nut","points":96040,"regions":["Varlamore","Karamja","Kandarin","Tirannwn","Kebos and Kourend"]},{"rank":22,"name":"Teaa Cup","points":96040,"regions":["Varlamore","Karamja","Kandarin","Tirannwn","Kebos and Kourend"]},{"rank":23,"name":"Wise Old Pal","points":96040,"regions":["Varlamore","Karamja","Kandarin","Tirannwn","Kebos and Kourend"]},{"rank":24,"name":"Baaze","points":96040,"regions":["Varlamore","Karamja","Kandarin","Tirannwn","Kebos and Kourend"]},{"rank":25,"name":"catsleep","points":96040,"regions":["Varlamore","Karamja","Kandarin","Tirannwn","Kebos and Kourend"]},{"rank":26,"name":"Gl Im Tom","points":96040,"regions":["Varlamore","Karamja","Kandarin","Tirannwn","Kebos and Kourend"]},{"rank":27,"name":"Pole Met","points":96040,"regions":["Varlamore","Karamja","Kandarin","Tirannwn","Kebos and Kourend"]},{"rank":28,"name":"Fehz","points":96040,"regions":["Varlamore","Karamja","Kandarin","Desert","Kebos and Kourend"]},{"rank":29,"name":"Schokotraum","points":96040,"regions":["Varlamore","Karamja","Kandarin","Tirannwn","Kebos and Kourend"]},{"rank":30,"name":"KiwiIskadda","points":96040,"regions":["Varlamore","Karamja","Kandarin","Tirannwn","Kebos and Kourend"]},{"rank":31,"name":"Anditre","points":96040,"regions":["Varlamore","Karamja","Kandarin","Tirannwn","Kebos and Kourend"]},{"rank":32,"name":"Usva","points":96040,"regions":["Varlamore","Karamja","Kandarin","Tirannwn","Kebos and Kourend"]},{"rank":33,"name":"Seanz","points":96040,"regions":["Varlamore","Karamja","Kandarin","Tirannwn","Kebos and Kourend"]},{"rank":34,"name":"Humble Otter","points":96040,"regions":["Varlamore","Karamja","Kandarin","Tirannwn","Kebos and Kourend"]},{"rank":35,"name":"DMMonkfish","points":96040,"regions":["Varlamore","Karamja","Kandarin","Tirannwn","Kebos and Kourend"]},{"rank":36,"name":"Figuur","points":96040,"regions":["Varlamore","Karamja","Kandarin","Tirannwn","Kebos and Kourend"]},{"rank":37,"name":"ImAGwiyomi","points":96040,"regions":["Varlamore","Karamja","Kandarin","Tirannwn","Kebos and Kourend"]},{"rank":38,"name":"Scottie","points":96040,"regions":["Varlamore","Karamja","Kandarin","Tirannwn","Kebos and Kourend"]},{"rank":39,"name":"Tokkul Hole","points":96040,"regions":["Varlamore","Karamja","Kandarin","Tirannwn","Kebos and Kourend"]},{"rank":40,"name":"Tyst","points":96040,"regions":["Varlamore","Karamja","Fremennik Province","Kandarin","Kebos and Kourend"]},{"rank":41,"name":"Ranger Lemus","points":96040,"regions":["Varlamore","Karamja","Kandarin","Tirannwn","Kebos and Kourend"]},{"rank":42,"name":"Molten B","points":96040,"regions":["Varlamore","Karamja","Kandarin","Tirannwn","Kebos and Kourend"]},{"rank":43,"name":"Exarch","points":96040,"regions":["Varlamore","Karamja","Kandarin","Tirannwn","Kebos and Kourend"]},{"rank":44,"name":"Satamario","points":96040,"regions":["Varlamore","Karamja","Kandarin","Tirannwn","Kebos and Kourend"]},{"rank":45,"name":"Maverick Btw","points":96040,"regions":["Varlamore","Karamja","Kandarin","Tirannwn","Kebos and Kourend"]},{"rank":46,"name":"Trattil","points":96040,"regions":["Varlamore","Karamja","Asgarnia","Kandarin","Morytania"]},{"rank":47,"name":"Opayye","points":96040,"regions":["Varlamore","Karamja","Asgarnia","Kandarin","Kebos and Kourend"]},{"rank":48,"name":"Psychia Tree","points":96040,"regions":["Varlamore","Karamja","Kandarin","Desert","Kebos and Kourend"]},{"rank":49,"name":"dippy eggs","points":96040,"regions":["Varlamore","Karamja","Kandarin","Tirannwn","Kebos and Kourend"]},{"rank":50,"name":"Kilzu","points":96040,"regions":["Varlamore","Karamja","Kandarin","Tirannwn","Kebos and Kourend"]},{"rank":51,"name":"Zekkels","points":96040,"regions":["Varlamore","Karamja","Kandarin","Tirannwn","Kebos and Kourend"]},{"rank":52,"name":"AG up ur S","points":96040,"regions":["Varlamore","Karamja","Kandarin","Tirannwn","Kebos and Kourend"]},{"rank":53,"name":"Slick Lenny","points":96040,"regions":["Varlamore","Karamja","Kandarin","Tirannwn","Kebos and Kourend"]},{"rank":54,"name":"Wardy791","points":96040,"regions":["Varlamore","Karamja","Kandarin","Tirannwn","Kebos and Kourend"]},{"rank":55,"name":"BEATONiT","points":96040,"regions":["Varlamore","Karamja","Kandarin","Desert","Kebos and Kourend"]},{"rank":56,"name":"MugiWugi","points":96040,"regions":["Varlamore","Karamja","Kandarin","Tirannwn","Kebos and Kourend"]},{"rank":57,"name":"infinite","points":96040,"regions":["Varlamore","Karamja","Kandarin","Tirannwn","Kebos and Kourend"]},{"rank":58,"name":"Goodfellow","points":96040,"regions":["Varlamore","Karamja","Kandarin","Tirannwn","Kebos and Kourend"]},{"rank":59,"name":"Tickflow","points":96040,"regions":["Varlamore","Karamja","Kandarin","Tirannwn","Kebos and Kourend"]},{"rank":60,"name":"chud monkey","points":96040,"regions":["Varlamore","Karamja","Kandarin","Tirannwn","Kebos and Kourend"]},{"rank":61,"name":"Iron Laura1","points":96040,"regions":["Varlamore","Karamja","Kandarin","Tirannwn","Kebos and Kourend"]},{"rank":62,"name":"Suplybox","points":96040,"regions":["Varlamore","Karamja","Kandarin","Tirannwn","Kebos and Kourend"]},{"rank":63,"name":"I was Krazy","points":96040,"regions":["Varlamore","Karamja","Kandarin","Tirannwn","Kebos and Kourend"]},{"rank":64,"name":"WIDE POGGIES","points":96040,"regions":["Varlamore","Karamja","Kandarin","Tirannwn","Kebos and Kourend"]},{"rank":65,"name":"Glooknar","points":96040,"regions":["Varlamore","Karamja","Kandarin","Tirannwn","Kebos and Kourend"]},{"rank":66,"name":"ruorimies","points":96040,"regions":["Varlamore","Karamja","Kandarin","Tirannwn","Kebos and Kourend"]},{"rank":67,"name":"Twirlylimon","points":96040,"regions":["Varlamore","Karamja","Kandarin","Tirannwn","Kebos and Kourend"]},{"rank":68,"name":"Crangus","points":96040,"regions":["Varlamore","Karamja","Kandarin","Morytania","Tirannwn"]},{"rank":69,"name":"Corgi Puppy","points":96040,"regions":["Varlamore","Karamja","Kandarin","Tirannwn","Kebos and Kourend"]},{"rank":70,"name":"Dohdee","points":96040,"regions":["Varlamore","Karamja","Kandarin","Tirannwn","Kebos and Kourend"]},{"rank":71,"name":"Losel","points":96040,"regions":["Varlamore","Karamja","Kandarin","Tirannwn","Kebos and Kourend"]},{"rank":72,"name":"LGBTQIDGAF","points":96040,"regions":["Varlamore","Karamja","Kandarin","Tirannwn","Kebos and Kourend"]},{"rank":73,"name":"Iron_Nino07","points":96040,"regions":["Varlamore","Karamja","Kandarin","Tirannwn","Kebos and Kourend"]},{"rank":74,"name":"Mina Heart 2","points":96040,"regions":["Varlamore","Karamja","Kandarin","Tirannwn","Kebos and Kourend"]},{"rank":75,"name":"Jettrider","points":96040,"regions":["Varlamore","Karamja","Kandarin","Tirannwn","Kebos and Kourend"]},{"rank":76,"name":"Lord Devil","points":96040,"regions":["Varlamore","Karamja","Asgarnia","Kandarin","Desert"]},{"rank":77,"name":"cabamx","points":96040,"regions":["Varlamore","Karamja","Kandarin","Tirannwn","Kebos and Kourend"]},{"rank":78,"name":"Tev0","points":96040,"regions":["Varlamore","Karamja","Kandarin","Tirannwn","Kebos and Kourend"]},{"rank":79,"name":"0ukashi","points":96010,"regions":["Varlamore","Karamja","Kandarin","Tirannwn","Kebos and Kourend"]},{"rank":80,"name":"Fe IV","points":96010,"regions":["Varlamore","Karamja","Kandarin","Tirannwn","Kebos and Kourend"]},{"rank":81,"name":"sssssssk","points":96010,"regions":["Varlamore","Karamja","Kandarin","Tirannwn","Kebos and Kourend"]},{"rank":82,"name":"Eskett","points":96010,"regions":["Varlamore","Karamja","Kandarin","Tirannwn","Kebos and Kourend"]},{"rank":83,"name":"ChadMilk","points":95840,"regions":["Varlamore","Karamja","Kandarin","Tirannwn","Kebos and Kourend"]},{"rank":84,"name":"TimShutDown","points":95640,"regions":["Varlamore","Karamja","Kandarin","Morytania","Tirannwn"]},{"rank":85,"name":"RautaLeksa","points":95240,"regions":["Varlamore","Karamja","Asgarnia","Tirannwn","Kebos and Kourend"]},{"rank":86,"name":"Kind Ghost","points":95240,"regions":["Varlamore","Karamja","Kandarin","Tirannwn","Kebos and Kourend"]},{"rank":87,"name":"Whomst MD","points":95240,"regions":["Varlamore","Karamja","Kandarin","Tirannwn","Kebos and Kourend"]},{"rank":88,"name":"Ferrothan","points":95040,"regions":["Varlamore","Karamja","Kandarin","Tirannwn","Kebos and Kourend"]},{"rank":89,"name":"smelvin osrs","points":95040,"regions":["Varlamore","Karamja","Kandarin","Tirannwn","Kebos and Kourend"]},{"rank":90,"name":"Alpha Wooper","points":94840,"regions":["Varlamore","Karamja","Kandarin","Tirannwn","Kebos and Kourend"]},{"rank":91,"name":"ttortt","points":94640,"regions":["Varlamore","Karamja","Asgarnia","Desert","Wilderness"]},{"rank":92,"name":"iFoRGe","points":94640,"regions":["Varlamore","Karamja","Kandarin","Tirannwn","Kebos and Kourend"]},{"rank":93,"name":"BinLidLicker","points":94380,"regions":["Varlamore","Karamja","Kandarin","Tirannwn","Kebos and Kourend"]},{"rank":94,"name":"Rowfy","points":94380,"regions":["Varlamore","Karamja","Kandarin","Desert","Kebos and Kourend"]},{"rank":95,"name":"Smartpants77","points":94240,"regions":["Varlamore","Karamja","Kandarin","Tirannwn","Kebos and Kourend"]},{"rank":96,"name":"Priority","points":94240,"regions":["Varlamore","Karamja","Asgarnia","Desert","Tirannwn"]},{"rank":97,"name":"HYPOXD","points":94140,"regions":["Varlamore","Karamja","Kandarin","Tirannwn","Kebos and Kourend"]},{"rank":98,"name":"ZOKUZOKU","points":94040,"regions":["Varlamore","Karamja","Kandarin","Tirannwn","Kebos and Kourend"]},{"rank":99,"name":"What Client","points":94010,"regions":["Varlamore","Karamja","Kandarin","Tirannwn","Kebos and Kourend"]},{"rank":100,"name":"Acdh Leagues","points":93930,"regions":["Varlamore","Karamja","Kandarin","Tirannwn","Kebos and Kourend"]},{"rank":101,"name":"Kuratheangel","points":93930,"regions":["Varlamore","Karamja","Desert","Tirannwn","Kebos and Kourend"]},{"rank":102,"name":"Kepuck","points":93840,"regions":["Varlamore","Karamja","Kandarin","Tirannwn","Kebos and Kourend"]},{"rank":103,"name":"EXpoZuR Fe","points":93840,"regions":["Varlamore","Karamja","Kandarin","Tirannwn","Kebos and Kourend"]},{"rank":104,"name":"Spyx","points":93840,"regions":["Varlamore","Karamja","Kandarin","Tirannwn","Kebos and Kourend"]},{"rank":105,"name":"Xerkom","points":93840,"regions":["Varlamore","Karamja","Kandarin","Tirannwn","Kebos and Kourend"]},{"rank":106,"name":"Free Laupie","points":93810,"regions":["Varlamore","Karamja","Kandarin","Morytania","Tirannwn"]},{"rank":107,"name":"D runk","points":93800,"regions":["Varlamore","Karamja","Kandarin","Morytania","Tirannwn"]},{"rank":108,"name":"Yogy Bear","points":93530,"regions":["Varlamore","Karamja","Asgarnia","Kandarin","Desert"]},{"rank":109,"name":"Akicha","points":93440,"regions":["Varlamore","Karamja","Kandarin","Tirannwn","Kebos and Kourend"]},{"rank":110,"name":"Vyraal1","points":93420,"regions":["Varlamore","Karamja","Kandarin","Tirannwn","Kebos and Kourend"]},{"rank":111,"name":"Sunstriker","points":93380,"regions":["Varlamore","Karamja","Kandarin","Tirannwn","Kebos and Kourend"]},{"rank":112,"name":"rautsa123","points":93280,"regions":["Varlamore","Karamja","Kandarin","Morytania","Tirannwn"]},{"rank":113,"name":"PureUanubis","points":93240,"regions":["Varlamore","Karamja","Kandarin","Wilderness","Kebos and Kourend"]},{"rank":114,"name":"Guarde d","points":93240,"regions":["Varlamore","Karamja","Kandarin","Tirannwn","Kebos and Kourend"]},{"rank":115,"name":"IdkmybffUIM","points":92960,"regions":["Varlamore","Karamja","Kandarin","Tirannwn","Kebos and Kourend"]},{"rank":116,"name":"Aykon","points":92850,"regions":["Varlamore","Karamja","Kandarin","Tirannwn","Kebos and Kourend"]},{"rank":117,"name":"Nylocke","points":92840,"regions":["Varlamore","Karamja","Kandarin","Tirannwn","Kebos and Kourend"]},{"rank":118,"name":"Caramel Bean","points":92840,"regions":["Varlamore","Karamja","Kandarin","Tirannwn","Kebos and Kourend"]},{"rank":119,"name":"BIG GREEEZY","points":92840,"regions":["Varlamore","Karamja","Asgarnia","Desert","Kebos and Kourend"]},{"rank":120,"name":"Fire Tempest","points":92840,"regions":["Varlamore","Karamja","Kandarin","Tirannwn","Kebos and Kourend"]},{"rank":121,"name":"Prison Vyn","points":92760,"regions":["Varlamore","Karamja","Kandarin","Tirannwn","Kebos and Kourend"]},{"rank":122,"name":"Miracore","points":92680,"regions":["Varlamore","Karamja","Kandarin","Morytania","Tirannwn"]},{"rank":123,"name":"Gary Parry","points":92640,"regions":["Varlamore","Karamja","Kandarin","Morytania","Tirannwn"]},{"rank":124,"name":"llIIlllIll","points":92610,"regions":["Varlamore","Karamja","Kandarin","Morytania","Tirannwn"]},{"rank":125,"name":"Brieenne","points":92610,"regions":["Varlamore","Karamja","Kandarin","Tirannwn","Kebos and Kourend"]},{"rank":126,"name":"MilloWSmile","points":92600,"regions":[]},{"rank":127,"name":"Vivascape","points":92570,"regions":["Varlamore","Karamja","Kandarin","Tirannwn","Kebos and Kourend"]},{"rank":128,"name":"D4mon","points":92560,"regions":["Varlamore","Karamja","Kandarin","Tirannwn","Kebos and Kourend"]},{"rank":129,"name":"SeaMenIron","points":92560,"regions":["Varlamore","Karamja","Kandarin","Morytania","Tirannwn"]},{"rank":130,"name":"LamboDoge","points":92490,"regions":["Varlamore","Karamja","Kandarin","Morytania","Tirannwn"]},{"rank":131,"name":"jere larm","points":92440,"regions":["Varlamore","Karamja","Kandarin","Tirannwn","Kebos and Kourend"]},{"rank":132,"name":"Noodle Ween","points":92370,"regions":["Varlamore","Karamja","Kandarin","Tirannwn","Kebos and Kourend"]},{"rank":133,"name":"SaekeaS","points":92360,"regions":["Varlamore","Karamja","Kandarin","Morytania","Tirannwn"]},{"rank":134,"name":"Tenhou","points":92300,"regions":["Varlamore","Karamja","Kandarin","Tirannwn","Kebos and Kourend"]},{"rank":135,"name":"Cheese Toast","points":92210,"regions":["Varlamore","Karamja","Kandarin","Morytania","Tirannwn"]},{"rank":136,"name":"Pie Pizza4","points":92180,"regions":["Varlamore","Karamja","Kandarin","Tirannwn","Kebos and Kourend"]},{"rank":137,"name":"Clem585","points":92040,"regions":["Varlamore","Karamja","Kandarin","Tirannwn","Kebos and Kourend"]},{"rank":138,"name":"Destroyerzim","points":92010,"regions":["Varlamore","Karamja","Kandarin","Tirannwn","Kebos and Kourend"]},{"rank":139,"name":"MrBoss","points":91930,"regions":[]},{"rank":140,"name":"Ultim8 Kevin","points":91840,"regions":[]},{"rank":141,"name":"Twinr0va","points":91670,"regions":[]},{"rank":142,"name":"GusGud","points":91610,"regions":["Varlamore","Karamja","Kandarin","Tirannwn","Kebos and Kourend"]},{"rank":143,"name":"Mevvz","points":91610,"regions":["Varlamore","Karamja","Kandarin","Tirannwn","Wilderness"]},{"rank":144,"name":"A Dumb Rat","points":91610,"regions":["Varlamore","Karamja","Tirannwn","Wilderness","Kebos and Kourend"]},{"rank":145,"name":"shkoBo","points":91600,"regions":[]},{"rank":146,"name":"I B Z","points":91570,"regions":["Varlamore","Karamja","Kandarin","Tirannwn","Kebos and Kourend"]},{"rank":147,"name":"Ostermark","points":91520,"regions":["Varlamore","Karamja","Kandarin","Tirannwn","Kebos and Kourend"]},{"rank":148,"name":"BearDown80","points":91480,"regions":[]},{"rank":149,"name":"Simp Andy","points":91450,"regions":["Varlamore","Karamja","Kandarin","Tirannwn","Kebos and Kourend"]},{"rank":150,"name":"purpleyukari","points":91440,"regions":[]},{"rank":151,"name":"Grimy Oppie","points":91440,"regions":["Varlamore","Karamja","Kandarin","Morytania","Tirannwn"]},{"rank":152,"name":"BobbyVagana","points":91440,"regions":[]},{"rank":153,"name":"Kint","points":91410,"regions":["Varlamore","Karamja","Kandarin","Tirannwn","Kebos and Kourend"]},{"rank":154,"name":"Calc OS","points":91400,"regions":[]},{"rank":155,"name":"Ludicolo","points":91330,"regions":[]},{"rank":156,"name":"notfudgebear","points":91320,"regions":[]},{"rank":157,"name":"Erbal","points":91250,"regions":["Varlamore","Karamja","Kandarin","Morytania","Tirannwn"]},{"rank":158,"name":"Fallen Album","points":91240,"regions":[]},{"rank":159,"name":"Iron Chemic","points":91210,"regions":["Varlamore","Karamja","Asgarnia","Kandarin","Tirannwn"]},{"rank":160,"name":"xPhil","points":91160,"regions":["Varlamore","Karamja","Kandarin","Morytania","Tirannwn"]},{"rank":161,"name":"ProDbeast","points":91080,"regions":[]},{"rank":162,"name":"Nyhlo","points":91010,"regions":["Varlamore","Karamja","Kandarin","Tirannwn","Kebos and Kourend"]},{"rank":163,"name":"Loosh","points":90900,"regions":["Varlamore","Karamja","Fremennik Province","Desert","Tirannwn"]},{"rank":164,"name":"56 Bunny 27","points":90860,"regions":["Varlamore","Karamja","Kandarin","Wilderness","Kebos and Kourend"]},{"rank":165,"name":"KingOfUIM","points":90840,"regions":["Varlamore","Karamja","Tirannwn","Wilderness","Kebos and Kourend"]},{"rank":166,"name":"Pepsomaster","points":90760,"regions":["Varlamore","Karamja","Kandarin","Tirannwn","Kebos and Kourend"]},{"rank":167,"name":"TumblingSand","points":90730,"regions":["Varlamore","Karamja","Asgarnia","Desert","Wilderness"]},{"rank":168,"name":"ThiccySnacc","points":90680,"regions":["Varlamore","Karamja","Fremennik Province","Desert","Wilderness"]},{"rank":169,"name":"Gertheroy","points":90640,"regions":["Varlamore","Karamja","Kandarin","Desert","Kebos and Kourend"]},{"rank":170,"name":"ratt nuts","points":90620,"regions":[]},{"rank":171,"name":"C4R3Y","points":90610,"regions":["Varlamore","Karamja","Kandarin","Tirannwn","Kebos and Kourend"]},{"rank":172,"name":"Albm","points":90590,"regions":["Varlamore","Karamja","Morytania","Tirannwn","Wilderness"]},{"rank":173,"name":"Suqmah Nips","points":90500,"regions":["Varlamore","Karamja","Kandarin","Tirannwn","Kebos and Kourend"]},{"rank":174,"name":"Spuhcific","points":90450,"regions":["Varlamore","Karamja","Kandarin","Morytania","Tirannwn"]},{"rank":175,"name":"Gerald Fjord","points":90450,"regions":[]},{"rank":176,"name":"Barkieboy3","points":90340,"regions":[]},{"rank":177,"name":"Akyrum","points":90300,"regions":["Varlamore","Karamja","Kandarin","Tirannwn","Kebos and Kourend"]},{"rank":178,"name":"Wengus","points":90280,"regions":[]},{"rank":179,"name":"benns","points":90250,"regions":["Varlamore","Karamja","Desert","Tirannwn","Wilderness"]},{"rank":180,"name":"Willi","points":90250,"regions":["Varlamore","Karamja","Kandarin","Tirannwn","Kebos and Kourend"]},{"rank":181,"name":"Danskarmel","points":90240,"regions":["Varlamore","Karamja","Asgarnia","Kandarin","Morytania"]},{"rank":182,"name":"infra low","points":90170,"regions":["Varlamore","Karamja","Kandarin","Morytania","Tirannwn"]},{"rank":183,"name":"IndiefoxxSub","points":90160,"regions":["Varlamore","Karamja","Kandarin","Tirannwn","Kebos and Kourend"]},{"rank":184,"name":"Hoppip","points":90110,"regions":["Varlamore","Karamja","Kandarin","Morytania","Tirannwn"]},{"rank":185,"name":"LazyFkTurtle","points":90100,"regions":["Varlamore","Karamja","Kandarin","Tirannwn","Kebos and Kourend"]},{"rank":186,"name":"Speed Wobble","points":90060,"regions":[]},{"rank":187,"name":"zalttar","points":90040,"regions":[]},{"rank":188,"name":"J uun","points":90030,"regions":["Varlamore","Karamja","Kandarin","Tirannwn","Kebos and Kourend"]},{"rank":189,"name":"Xtreme Log","points":90020,"regions":["Varlamore","Karamja","Kandarin","Tirannwn","Wilderness"]},{"rank":190,"name":"TurboSueless","points":90000,"regions":[]},{"rank":191,"name":"fwapdokopjai","points":89930,"regions":[]},{"rank":192,"name":"Figen","points":89850,"regions":[]},{"rank":193,"name":"eepy eggo","points":89840,"regions":["Varlamore","Karamja","Kandarin","Tirannwn","Kebos and Kourend"]},{"rank":194,"name":"elmo te hobo","points":89820,"regions":[]},{"rank":195,"name":"bg bonqueror","points":89780,"regions":[]},{"rank":196,"name":"IronTau","points":89780,"regions":[]},{"rank":197,"name":"Jah toch","points":89730,"regions":["Varlamore","Karamja","Kandarin","Tirannwn","Kebos and Kourend"]},{"rank":198,"name":"jjiinnii","points":89720,"regions":[]},{"rank":199,"name":"No Bols","points":89680,"regions":["Varlamore","Karamja","Asgarnia","Tirannwn","Kebos and Kourend"]},{"rank":200,"name":"Royn","points":89640,"regions":[]},{"rank":201,"name":"TYC Beatrice","points":89570,"regions":["Varlamore","Karamja","Kandarin","Morytania","Tirannwn"]},{"rank":202,"name":"sembino","points":89530,"regions":["Varlamore","Karamja","Kandarin","Morytania","Tirannwn"]},{"rank":203,"name":"Iron Stee1","points":89500,"regions":[]},{"rank":204,"name":"ass chance","points":89480,"regions":[]},{"rank":205,"name":"Zamorakussy","points":89440,"regions":["Varlamore","Karamja","Kandarin","Tirannwn","Kebos and Kourend"]},{"rank":206,"name":"Zwakke Dog","points":89430,"regions":["Varlamore","Karamja","Kandarin","Tirannwn","Kebos and Kourend"]},{"rank":207,"name":"Geo Tasker","points":89400,"regions":["Varlamore","Karamja","Kandarin","Desert","Kebos and Kourend"]},{"rank":208,"name":"Valdevon","points":89350,"regions":["Varlamore","Karamja","Kandarin","Tirannwn","Kebos and Kourend"]},{"rank":209,"name":"30 min Break","points":89320,"regions":[]},{"rank":210,"name":"kebabwfries","points":89310,"regions":["Varlamore","Karamja","Kandarin","Tirannwn","Kebos and Kourend"]},{"rank":211,"name":"Ph0fz PvE","points":89260,"regions":["Varlamore","Karamja","Morytania","Tirannwn","Wilderness"]},{"rank":212,"name":"WheresBank","points":89170,"regions":[]},{"rank":213,"name":"Cookiezi","points":89080,"regions":[]},{"rank":214,"name":"Voetbalkous","points":89010,"regions":["Varlamore","Karamja","Kandarin","Tirannwn","Kebos and Kourend"]},{"rank":215,"name":"Typo Negativ","points":89010,"regions":["Varlamore","Karamja","Kandarin","Morytania","Tirannwn"]},{"rank":216,"name":"Abysmal Luck","points":89010,"regions":["Varlamore","Karamja","Fremennik Province","Kandarin","Kebos and Kourend"]},{"rank":217,"name":"OWCA_UwU","points":88900,"regions":[]},{"rank":218,"name":"GIM Solarce","points":88880,"regions":[]},{"rank":219,"name":"Gandorian","points":88880,"regions":[]},{"rank":220,"name":"Dyselexic","points":88810,"regions":["Varlamore","Karamja","Kandarin","Tirannwn","Kebos and Kourend"]},{"rank":221,"name":"Edwin","points":88800,"regions":[]},{"rank":222,"name":"L6 xip","points":88760,"regions":[]},{"rank":223,"name":"UncleMumble","points":88760,"regions":[]},{"rank":224,"name":"Craftwolf IM","points":88740,"regions":["Varlamore","Karamja","Kandarin","Tirannwn","Kebos and Kourend"]},{"rank":225,"name":"MrMonsterous","points":88680,"regions":["Varlamore","Karamja","Kandarin","Tirannwn","Kebos and Kourend"]},{"rank":226,"name":"Corun","points":88660,"regions":["Varlamore","Karamja","Kandarin","Tirannwn","Kebos and Kourend"]},{"rank":227,"name":"iDeadmen","points":88640,"regions":["Varlamore","Karamja","Kandarin","Morytania","Tirannwn"]},{"rank":228,"name":"Big rOve","points":88610,"regions":["Varlamore","Karamja","Kandarin","Tirannwn","Kebos and Kourend"]},{"rank":229,"name":"O o g a","points":88610,"regions":[]},{"rank":230,"name":"Kits","points":88570,"regions":["Varlamore","Karamja","Kandarin","Morytania","Tirannwn"]},{"rank":231,"name":"EGirl Marcy","points":88560,"regions":["Varlamore","Karamja","Kandarin","Morytania","Tirannwn"]},{"rank":232,"name":"Kacy","points":88560,"regions":["Varlamore","Karamja","Asgarnia","Kandarin","Kebos and Kourend"]},{"rank":233,"name":"Zwiers","points":88530,"regions":[]},{"rank":234,"name":"Romalty","points":88450,"regions":["Varlamore","Karamja","Kandarin","Tirannwn","Wilderness"]},{"rank":235,"name":"Sidebirb4","points":88440,"regions":[]},{"rank":236,"name":"kuu-ukko","points":88340,"regions":["Varlamore","Karamja","Asgarnia","Desert","Kebos and Kourend"]},{"rank":237,"name":"Suhppliedr","points":88310,"regions":[]},{"rank":238,"name":"I am J M E","points":88240,"regions":[]},{"rank":239,"name":"Jwai GIM","points":88240,"regions":["Varlamore","Karamja","Kandarin","Morytania","Tirannwn"]},{"rank":240,"name":"Typhlosion","points":88240,"regions":["Varlamore","Karamja","Kandarin","Tirannwn","Kebos and Kourend"]},{"rank":241,"name":"Innate Light","points":88210,"regions":["Varlamore","Karamja","Kandarin","Tirannwn","Kebos and Kourend"]},{"rank":242,"name":"Tidev","points":88200,"regions":[]},{"rank":243,"name":"Half Jewish","points":88060,"regions":[]},{"rank":244,"name":"Bally 20","points":87920,"regions":[]},{"rank":245,"name":"wtbExile","points":87900,"regions":["Varlamore","Karamja","Kandarin","Tirannwn","Kebos and Kourend"]},{"rank":246,"name":"DR HYPE","points":87890,"regions":[]},{"rank":247,"name":"Vizua","points":87840,"regions":["Varlamore","Karamja","Kandarin","Tirannwn","Kebos and Kourend"]},{"rank":248,"name":"GIM Hypno","points":87840,"regions":["Varlamore","Karamja","Kandarin","Tirannwn","Kebos and Kourend"]},{"rank":249,"name":"Jordie","points":87800,"regions":[]},{"rank":250,"name":"JUQQER","points":87780,"regions":[]},{"rank":251,"name":"Single Nug","points":87760,"regions":["Varlamore","Karamja","Kandarin","Morytania","Tirannwn"]},{"rank":252,"name":"Ressaca","points":87740,"regions":["Varlamore","Karamja","Asgarnia","Tirannwn","Kebos and Kourend"]},{"rank":253,"name":"evonaabi","points":87740,"regions":["Varlamore","Karamja","Asgarnia","Wilderness","Kebos and Kourend"]},{"rank":254,"name":"TheKizzler","points":87650,"regions":[]},{"rank":255,"name":"The OSU","points":87630,"regions":[]},{"rank":256,"name":"N P L E","points":87580,"regions":[]},{"rank":257,"name":"mattrabbit","points":87520,"regions":["Varlamore","Karamja","Tirannwn","Wilderness","Kebos and Kourend"]},{"rank":258,"name":"SkinTone5","points":87490,"regions":[]},{"rank":259,"name":"Jarbo52","points":87470,"regions":[]},{"rank":260,"name":"rooiegerr1t","points":87440,"regions":[]},{"rank":261,"name":"sheep5","points":87410,"regions":["Varlamore","Karamja","Fremennik Province","Kandarin","Kebos and Kourend"]},{"rank":262,"name":"MikaDMM","points":87380,"regions":["Varlamore","Karamja","Kandarin","Tirannwn","Wilderness"]},{"rank":263,"name":"lilpissbby","points":87380,"regions":["Varlamore","Karamja","Morytania","Tirannwn","Wilderness"]},{"rank":264,"name":"Quest Plug","points":87370,"regions":["Varlamore","Karamja","Asgarnia","Kandarin","Kebos and Kourend"]},{"rank":265,"name":"What Sleep","points":87370,"regions":[]},{"rank":266,"name":"Gohas","points":87350,"regions":[]},{"rank":267,"name":"Iron Kodie","points":87320,"regions":["Varlamore","Karamja","Kandarin","Morytania","Tirannwn"]},{"rank":268,"name":"Frederikki","points":87260,"regions":["Varlamore","Karamja","Kandarin","Tirannwn","Kebos and Kourend"]},{"rank":269,"name":"Tasktician","points":87260,"regions":[]},{"rank":270,"name":"Gigga Gapper","points":87250,"regions":["Varlamore","Karamja","Kandarin","Morytania","Tirannwn"]},{"rank":271,"name":"sadturtle74","points":87210,"regions":["Varlamore","Karamja","Kandarin","Desert","Kebos and Kourend"]},{"rank":272,"name":"TakinShots","points":87100,"regions":[]},{"rank":273,"name":"ticketfiend","points":87090,"regions":["Varlamore","Karamja","Kandarin","Tirannwn","Wilderness"]},{"rank":274,"name":"YoloSwagHope","points":87060,"regions":["Varlamore","Karamja","Kandarin","Morytania","Tirannwn"]},{"rank":275,"name":"Dekai Oppai","points":87030,"regions":["Varlamore","Karamja","Kandarin","Tirannwn","Kebos and Kourend"]},{"rank":276,"name":"Above","points":87020,"regions":[]},{"rank":277,"name":"TzTokGIMSock","points":86940,"regions":["Varlamore","Karamja","Asgarnia","Kandarin","Kebos and Kourend"]},{"rank":278,"name":"SamNotWise","points":86940,"regions":[]},{"rank":279,"name":"Iron Equity","points":86930,"regions":[]},{"rank":280,"name":"Lyp","points":86810,"regions":[]},{"rank":281,"name":"HyperFire12","points":86780,"regions":[]},{"rank":282,"name":"Reesy","points":86620,"regions":["Varlamore","Karamja","Kandarin","Tirannwn","Kebos and Kourend"]},{"rank":283,"name":"Gay Squire","points":86550,"regions":[]},{"rank":284,"name":"Big Smartass","points":86530,"regions":["Varlamore","Karamja","Asgarnia","Kandarin","Kebos and Kourend"]},{"rank":285,"name":"porkchop1234","points":86470,"regions":["Varlamore","Karamja","Kandarin","Tirannwn","Wilderness"]},{"rank":286,"name":"Ily Btw","points":86460,"regions":["Varlamore","Karamja","Kandarin","Morytania","Tirannwn"]},{"rank":287,"name":"GIM AF KING","points":86440,"regions":[]},{"rank":288,"name":"HispAzn","points":86420,"regions":[]},{"rank":289,"name":"Curry Cartel","points":86410,"regions":[]},{"rank":290,"name":"Sqirttle","points":86410,"regions":["Varlamore","Karamja","Kandarin","Tirannwn","Kebos and Kourend"]},{"rank":291,"name":"Anthonen","points":86400,"regions":[]},{"rank":292,"name":"Corona Bat","points":86400,"regions":[]},{"rank":293,"name":"D 50","points":86390,"regions":[]},{"rank":294,"name":"Dag Prime","points":86370,"regions":[]},{"rank":295,"name":"51drun","points":86360,"regions":[]},{"rank":296,"name":"Tz-Xeus-Guz","points":86360,"regions":["Varlamore","Karamja","Kandarin","Tirannwn","Kebos and Kourend"]},{"rank":297,"name":"Murt15","points":86310,"regions":[]},{"rank":298,"name":"DJ Llama","points":86310,"regions":["Varlamore","Karamja","Kandarin","Desert","Tirannwn"]},{"rank":299,"name":"Beralf","points":86280,"regions":["Varlamore","Karamja","Kandarin","Tirannwn","Wilderness"]},{"rank":300,"name":"GIM Keo","points":86270,"regions":[]},{"rank":301,"name":"StiifasIron","points":86220,"regions":[]},{"rank":302,"name":"Syh","points":86190,"regions":["Varlamore","Karamja","Kandarin","Wilderness","Kebos and Kourend"]},{"rank":303,"name":"EvilAllAlone","points":86170,"regions":[]},{"rank":304,"name":"TH5","points":86160,"regions":["Varlamore","Karamja","Kandarin","Morytania","Tirannwn"]},{"rank":305,"name":"IronKenna","points":86160,"regions":["Varlamore","Karamja","Kandarin","Tirannwn","Kebos and Kourend"]},{"rank":306,"name":"UIMycologist","points":86120,"regions":[]},{"rank":307,"name":"TheRealKyle","points":86110,"regions":["Varlamore","Karamja","Kandarin","Morytania","Tirannwn"]},{"rank":308,"name":"Maza","points":86070,"regions":[]},{"rank":309,"name":"Fun To Kill","points":86010,"regions":["Varlamore","Karamja","Kandarin","Morytania","Tirannwn"]},{"rank":310,"name":"Avaigo","points":86000,"regions":["Varlamore","Karamja","Kandarin","Tirannwn","Kebos and Kourend"]},{"rank":311,"name":"1337 RED","points":86000,"regions":[]},{"rank":312,"name":"Plondreim","points":85940,"regions":["Varlamore","Karamja","Kandarin","Morytania","Tirannwn"]},{"rank":313,"name":"HengeDied","points":85880,"regions":[]},{"rank":314,"name":"IM Andre","points":85880,"regions":[]},{"rank":315,"name":"Promoz","points":85850,"regions":["Varlamore","Karamja","Fremennik Province","Wilderness","Kebos and Kourend"]},{"rank":316,"name":"Maikhol","points":85820,"regions":["Varlamore","Karamja","Kandarin","Tirannwn","Kebos and Kourend"]},{"rank":317,"name":"D B Cooper","points":85810,"regions":["Varlamore","Karamja","Kandarin","Tirannwn","Kebos and Kourend"]},{"rank":318,"name":"SoGangsta","points":85810,"regions":["Varlamore","Karamja","Kandarin","Wilderness","Kebos and Kourend"]},{"rank":319,"name":"MickeyJoe","points":85810,"regions":[]},{"rank":320,"name":"Rxss","points":85720,"regions":["Varlamore","Karamja","Kandarin","Morytania","Kebos and Kourend"]},{"rank":321,"name":"IBuyGP","points":85710,"regions":["Varlamore","Karamja","Kandarin","Desert","Wilderness"]},{"rank":322,"name":"LoraxLem","points":85650,"regions":["Varlamore","Karamja","Kandarin","Tirannwn","Kebos and Kourend"]},{"rank":323,"name":"mr antifa","points":85640,"regions":[]},{"rank":324,"name":"Wax i","points":85640,"regions":["Varlamore","Karamja","Kandarin","Morytania","Kebos and Kourend"]},{"rank":325,"name":"Costef","points":85620,"regions":["Varlamore","Karamja","Kandarin","Tirannwn","Wilderness"]},{"rank":326,"name":"PhobosDeimos","points":85620,"regions":[]},{"rank":327,"name":"eL Destroyer","points":85570,"regions":[]},{"rank":328,"name":"Jafang","points":85560,"regions":[]},{"rank":329,"name":"D amz","points":85550,"regions":["Varlamore","Karamja","Asgarnia","Morytania","Tirannwn"]},{"rank":330,"name":"UnclelrohMan","points":85540,"regions":["Varlamore","Karamja","Kandarin","Tirannwn","Kebos and Kourend"]},{"rank":331,"name":"Hazz","points":85520,"regions":[]},{"rank":332,"name":"t urbo","points":85510,"regions":[]},{"rank":333,"name":"Mmorpg","points":85460,"regions":["Varlamore","Karamja","Morytania","Wilderness","Kebos and Kourend"]},{"rank":334,"name":"Glade Mamba","points":85440,"regions":[]},{"rank":335,"name":"TeeC","points":85420,"regions":[]},{"rank":336,"name":"Eksyin","points":85410,"regions":["Varlamore","Karamja","Kandarin","Morytania","Tirannwn"]},{"rank":337,"name":"Bioterrorism","points":85370,"regions":["Varlamore","Karamja","Asgarnia","Kandarin","Desert"]},{"rank":338,"name":"SpliffReload","points":85310,"regions":["Varlamore","Karamja","Kandarin","Tirannwn","Wilderness"]},{"rank":339,"name":"Wadsyy","points":85280,"regions":[]},{"rank":340,"name":"Kokoftu","points":85270,"regions":[]},{"rank":341,"name":"Brendonnee","points":85240,"regions":["Varlamore","Karamja","Morytania","Wilderness","Kebos and Kourend"]},{"rank":342,"name":"SkillerC4","points":85240,"regions":[]},{"rank":343,"name":"DoctorQuest","points":85230,"regions":[]},{"rank":344,"name":"SeaManTaster","points":85230,"regions":[]},{"rank":345,"name":"GIM Xyp9x","points":85210,"regions":["Varlamore","Karamja","Asgarnia","Kandarin","Wilderness"]},{"rank":346,"name":"Torresmo","points":85130,"regions":["Varlamore","Karamja","Kandarin","Morytania","Tirannwn"]},{"rank":347,"name":"No More Mory","points":85120,"regions":["Varlamore","Karamja","Asgarnia","Morytania","Tirannwn"]},{"rank":348,"name":"taas niiaa","points":85110,"regions":["Varlamore","Karamja","Kandarin","Tirannwn","Kebos and Kourend"]},{"rank":349,"name":"Lemon5000123","points":85080,"regions":["Varlamore","Karamja","Kandarin","Tirannwn","Kebos and Kourend"]},{"rank":350,"name":"XD PilleKope","points":85020,"regions":[]},{"rank":351,"name":"Tetsuma","points":85020,"regions":[]},{"rank":352,"name":"Pool Noodlez","points":85000,"regions":["Varlamore","Karamja","Kandarin","Morytania","Kebos and Kourend"]},{"rank":353,"name":"Hamza","points":84920,"regions":["Varlamore","Karamja","Kandarin","Tirannwn","Wilderness"]},{"rank":354,"name":"Vectors etc","points":84900,"regions":["Varlamore","Karamja","Kandarin","Wilderness","Kebos and Kourend"]},{"rank":355,"name":"WegCdbCdib","points":84860,"regions":["Varlamore","Karamja","Kandarin","Tirannwn","Kebos and Kourend"]},{"rank":356,"name":"Bosons","points":84850,"regions":[]},{"rank":357,"name":"Ricky rox","points":84850,"regions":["Varlamore","Karamja","Asgarnia","Kandarin","Kebos and Kourend"]},{"rank":358,"name":"Penward","points":84770,"regions":[]},{"rank":359,"name":"Sirius White","points":84720,"regions":[]},{"rank":360,"name":"fkrs","points":84720,"regions":[]},{"rank":361,"name":"Monster Tabz","points":84690,"regions":["Varlamore","Karamja","Kandarin","Tirannwn","Kebos and Kourend"]},{"rank":362,"name":"Litewarior","points":84690,"regions":[]},{"rank":363,"name":"Monokay","points":84690,"regions":[]},{"rank":364,"name":"flpi","points":84680,"regions":["Varlamore","Karamja","Asgarnia","Kandarin","Morytania"]},{"rank":365,"name":"Vorkathchan","points":84680,"regions":[]},{"rank":366,"name":"xDranik","points":84660,"regions":[]},{"rank":367,"name":"Read if Cute","points":84620,"regions":["Varlamore","Karamja","Kandarin","Tirannwn","Kebos and Kourend"]},{"rank":368,"name":"RudeTheTurk","points":84620,"regions":[]},{"rank":369,"name":"Unread","points":84600,"regions":[]},{"rank":370,"name":"FeCrustacean","points":84600,"regions":[]},{"rank":371,"name":"Fuzzy Chunks","points":84590,"regions":["Varlamore","Karamja","Kandarin","Tirannwn","Kebos and Kourend"]},{"rank":372,"name":"H iken","points":84580,"regions":["Varlamore","Karamja","Asgarnia","Kandarin","Kebos and Kourend"]},{"rank":373,"name":"Abella Safe","points":84570,"regions":["Varlamore","Karamja","Kandarin","Morytania","Tirannwn"]},{"rank":374,"name":"Snoop Rs","points":84530,"regions":["Varlamore","Karamja","Asgarnia","Kandarin","Kebos and Kourend"]},{"rank":375,"name":"Wimd","points":84520,"regions":["Varlamore","Karamja","Kandarin","Morytania","Tirannwn"]},{"rank":376,"name":"Cexiest Eva","points":84520,"regions":[]},{"rank":377,"name":"Hecke","points":84510,"regions":["Varlamore","Karamja","Kandarin","Tirannwn","Kebos and Kourend"]},{"rank":378,"name":"PointCapBofa","points":84500,"regions":[]},{"rank":379,"name":"Mok101","points":84460,"regions":["Varlamore","Karamja","Kandarin","Tirannwn","Wilderness"]},{"rank":380,"name":"AR JAX","points":84450,"regions":["Varlamore","Karamja","Asgarnia","Tirannwn","Kebos and Kourend"]},{"rank":381,"name":"ZoG Eth","points":84390,"regions":["Varlamore","Karamja","Kandarin","Morytania","Tirannwn"]},{"rank":382,"name":"Ugh Leagues","points":84380,"regions":["Varlamore","Karamja","Kandarin","Desert","Kebos and Kourend"]},{"rank":383,"name":"WowwSuchDoge","points":84360,"regions":[]},{"rank":384,"name":"Dew of Honey","points":84350,"regions":[]},{"rank":385,"name":"Darkoz","points":84350,"regions":[]},{"rank":386,"name":"0 eyecontact","points":84340,"regions":[]},{"rank":387,"name":"Bittykin","points":84330,"regions":["Varlamore","Karamja","Kandarin","Tirannwn","Kebos and Kourend"]},{"rank":388,"name":"Black User","points":84330,"regions":[]},{"rank":389,"name":"Iron Lose","points":84320,"regions":["Varlamore","Karamja","Kandarin","Tirannwn","Kebos and Kourend"]},{"rank":390,"name":"Lightcat","points":84320,"regions":[]},{"rank":391,"name":"Adambillys","points":84310,"regions":[]},{"rank":392,"name":"user536153","points":84300,"regions":["Varlamore","Karamja","Kandarin","Morytania","Tirannwn"]},{"rank":393,"name":"CrimsonWic","points":84290,"regions":[]},{"rank":394,"name":"Yamda","points":84290,"regions":["Varlamore","Karamja","Kandarin","Morytania","Tirannwn"]},{"rank":395,"name":"Ch arizard","points":84280,"regions":["Varlamore","Karamja","Kandarin","Tirannwn","Kebos and Kourend"]},{"rank":396,"name":"Macewindi","points":84280,"regions":[]},{"rank":397,"name":"Olm toe lick","points":84270,"regions":["Varlamore","Karamja","Kandarin","Tirannwn","Kebos and Kourend"]},{"rank":398,"name":"Y ogurt","points":84260,"regions":[]},{"rank":399,"name":"ozztrevor","points":84250,"regions":["Varlamore","Karamja","Kandarin","Tirannwn","Kebos and Kourend"]},{"rank":400,"name":"DB o","points":84220,"regions":[]},{"rank":401,"name":"Kail","points":84200,"regions":["Varlamore","Karamja","Kandarin","Morytania","Tirannwn"]},{"rank":402,"name":"BurdTheTurd","points":84170,"regions":[]},{"rank":403,"name":"Cycling Road","points":84140,"regions":[]},{"rank":404,"name":"K e vin","points":84140,"regions":[]},{"rank":405,"name":"Planks at P2","points":84100,"regions":[]},{"rank":406,"name":"IM Brandle","points":84090,"regions":[]},{"rank":407,"name":"Mell0wD","points":84080,"regions":[]},{"rank":408,"name":"BeQuietSpade","points":84040,"regions":[]},{"rank":409,"name":"Rhokk","points":84020,"regions":[]},{"rank":410,"name":"holymesiah","points":84010,"regions":["Varlamore","Karamja","Kandarin","Morytania","Tirannwn"]},{"rank":411,"name":"L0ck In","points":84000,"regions":["Varlamore","Karamja","Kandarin","Tirannwn","Wilderness"]},{"rank":412,"name":"Buchu Ballin","points":83980,"regions":["Varlamore","Karamja","Kandarin","Tirannwn","Kebos and Kourend"]},{"rank":413,"name":"ClarkyL","points":83970,"regions":["Varlamore","Karamja","Kandarin","Morytania","Tirannwn"]},{"rank":414,"name":"Seppiee","points":83930,"regions":[]},{"rank":415,"name":"Devonymous","points":83850,"regions":["Varlamore","Karamja","Kandarin","Morytania","Tirannwn"]},{"rank":416,"name":"Iron JLittle","points":83820,"regions":[]},{"rank":417,"name":"Miss Tazzie","points":83810,"regions":["Varlamore","Karamja","Kandarin","Tirannwn","Kebos and Kourend"]},{"rank":418,"name":"SirFroggits","points":83790,"regions":["Varlamore","Karamja","Kandarin","Morytania","Kebos and Kourend"]},{"rank":419,"name":"Ali the LiSs","points":83780,"regions":[]},{"rank":420,"name":"Can of Sham","points":83770,"regions":["Varlamore","Karamja","Kandarin","Desert","Tirannwn"]},{"rank":421,"name":"Ragequiter","points":83760,"regions":[]},{"rank":422,"name":"Hugakitty","points":83760,"regions":[]},{"rank":423,"name":"BalazinGIM","points":83740,"regions":[]},{"rank":424,"name":"ZamorakBrews","points":83720,"regions":["Varlamore","Karamja","Kandarin","Morytania","Tirannwn"]},{"rank":425,"name":"Shady Fred","points":83690,"regions":["Varlamore","Karamja","Kandarin","Tirannwn","Kebos and Kourend"]},{"rank":426,"name":"AVAWAVA","points":83650,"regions":[]},{"rank":427,"name":"dragon3046","points":83620,"regions":[]},{"rank":428,"name":"666 Brombeer","points":83620,"regions":["Varlamore","Karamja","Kandarin","Tirannwn","Kebos and Kourend"]},{"rank":429,"name":"Gwynrwyn","points":83620,"regions":["Varlamore","Karamja","Kandarin","Morytania","Tirannwn"]},{"rank":430,"name":"zeus energy","points":83610,"regions":[]},{"rank":431,"name":"SucksTehSuck","points":83600,"regions":[]},{"rank":432,"name":"Gim lisAxe","points":83590,"regions":[]},{"rank":433,"name":"Thats_NoGood","points":83570,"regions":["Varlamore","Karamja","Kandarin","Morytania","Kebos and Kourend"]},{"rank":434,"name":"Rin Kurenai","points":83560,"regions":["Varlamore","Karamja","Kandarin","Tirannwn","Wilderness"]},{"rank":435,"name":"Ironmanpimp","points":83500,"regions":[]},{"rank":436,"name":"Squeddy","points":83500,"regions":[]},{"rank":437,"name":"GIM Canan","points":83470,"regions":[]},{"rank":438,"name":"Tarmajin","points":83460,"regions":[]},{"rank":439,"name":"Stnmn","points":83460,"regions":[]},{"rank":440,"name":"Orcky","points":83450,"regions":["Varlamore","Karamja","Kandarin","Morytania","Tirannwn"]},{"rank":441,"name":"F aceless","points":83430,"regions":[]},{"rank":442,"name":"Owl Brother","points":83420,"regions":[]},{"rank":443,"name":"Abstand","points":83420,"regions":[]},{"rank":444,"name":"Echoloquate","points":83420,"regions":["Varlamore","Karamja","Kandarin","Tirannwn","Kebos and Kourend"]},{"rank":445,"name":"K una","points":83410,"regions":["Varlamore","Karamja","Kandarin","Morytania","Tirannwn"]},{"rank":446,"name":"Numb Fingers","points":83380,"regions":[]},{"rank":447,"name":"Apqle","points":83360,"regions":[]},{"rank":448,"name":"AbyssWalkerr","points":83350,"regions":[]},{"rank":449,"name":"5st","points":83330,"regions":[]},{"rank":450,"name":"SuperFlow","points":83230,"regions":["Varlamore","Karamja","Morytania","Tirannwn","Wilderness"]},{"rank":451,"name":"Daltdemption","points":83210,"regions":["Varlamore","Karamja","Kandarin","Tirannwn","Kebos and Kourend"]},{"rank":452,"name":"Sensou","points":83210,"regions":["Varlamore","Karamja","Kandarin","Tirannwn","Kebos and Kourend"]},{"rank":453,"name":"Tomocaust","points":83170,"regions":["Varlamore","Karamja","Kandarin","Tirannwn","Kebos and Kourend"]},{"rank":454,"name":"Jotwe","points":83160,"regions":["Varlamore","Karamja","Kandarin","Tirannwn","Wilderness"]},{"rank":455,"name":"Dr Chachii","points":83120,"regions":[]},{"rank":456,"name":"Macgyver5583","points":83110,"regions":["Varlamore","Karamja","Kandarin","Morytania","Tirannwn"]},{"rank":457,"name":"Morski","points":83100,"regions":["Varlamore","Karamja","Kandarin","Tirannwn","Wilderness"]},{"rank":458,"name":"Verolyze","points":83100,"regions":[]},{"rank":459,"name":"Annika","points":83100,"regions":[]},{"rank":460,"name":"Warez","points":83080,"regions":["Varlamore","Karamja","Kandarin","Tirannwn","Kebos and Kourend"]},{"rank":461,"name":"Bright Yang","points":83080,"regions":[]},{"rank":462,"name":"Thicck Fil A","points":83080,"regions":["Varlamore","Karamja","Tirannwn","Wilderness"]},{"rank":463,"name":"ZKill1O1","points":83080,"regions":[]},{"rank":464,"name":"Noog","points":83070,"regions":[]},{"rank":465,"name":"Ricklet","points":83070,"regions":[]},{"rank":466,"name":"Jane","points":83060,"regions":["Varlamore","Karamja","Kandarin","Tirannwn","Kebos and Kourend"]},{"rank":467,"name":"Fluffbunny6","points":83000,"regions":[]},{"rank":468,"name":"Piescension","points":82990,"regions":[]},{"rank":469,"name":"STRGTHS","points":82980,"regions":[]},{"rank":470,"name":"Lilpaleo","points":82970,"regions":[]},{"rank":471,"name":"0 Mime Law","points":82940,"regions":["Varlamore","Karamja","Kandarin","Tirannwn","Kebos and Kourend"]},{"rank":472,"name":"Northstar","points":82920,"regions":[]},{"rank":473,"name":"AxelsmithyIM","points":82910,"regions":[]},{"rank":474,"name":"T_Twinkle","points":82910,"regions":["Varlamore","Karamja","Kandarin","Tirannwn","Kebos and Kourend"]},{"rank":475,"name":"Iron Jon H","points":82900,"regions":[]},{"rank":476,"name":"19 Tall 2496","points":82890,"regions":["Varlamore","Karamja","Kandarin","Morytania","Tirannwn"]},{"rank":477,"name":"Kandalf","points":82890,"regions":["Varlamore","Karamja","Kandarin","Morytania","Tirannwn"]},{"rank":478,"name":"Pink Matter","points":82870,"regions":[]},{"rank":479,"name":"AaronDY","points":82850,"regions":[]},{"rank":480,"name":"t u k e","points":82830,"regions":[]},{"rank":481,"name":"Karliah","points":82820,"regions":[]},{"rank":482,"name":"BlueFanTuna","points":82820,"regions":[]},{"rank":483,"name":"Mmm Xp","points":82810,"regions":["Varlamore","Karamja","Fremennik Province","Wilderness","Kebos and Kourend"]},{"rank":484,"name":"Beeze","points":82810,"regions":[]},{"rank":485,"name":"Yo","points":82800,"regions":["Varlamore","Karamja","Kandarin","Tirannwn","Wilderness"]},{"rank":486,"name":"Witherwingz","points":82790,"regions":[]},{"rank":487,"name":"Dipindottzz","points":82750,"regions":[]},{"rank":488,"name":"PwincessEric","points":82750,"regions":[]},{"rank":489,"name":"Minotaurs","points":82740,"regions":["Varlamore","Karamja","Kandarin","Tirannwn","Kebos and Kourend"]},{"rank":490,"name":"Thirdwheelxd","points":82710,"regions":["Varlamore","Karamja","Tirannwn","Wilderness","Kebos and Kourend"]},{"rank":491,"name":"J0kkarn","points":82710,"regions":[]},{"rank":492,"name":"AG Suspect","points":82700,"regions":[]},{"rank":493,"name":"Aic","points":82660,"regions":[]},{"rank":494,"name":"sburzz","points":82620,"regions":[]},{"rank":495,"name":"GIM Yas","points":82620,"regions":[]},{"rank":496,"name":"Cl1ck Yellow","points":82600,"regions":[]},{"rank":497,"name":"Magnivore5","points":82600,"regions":[]},{"rank":498,"name":"Mammimara","points":82560,"regions":[]},{"rank":499,"name":"Auxilisea","points":82560,"regions":[]},{"rank":500,"name":"Rat Sensei","points":82520,"regions":[]}]}